aditor/__init__.py
aditor/core.py
aditor/py.typed
aditor-0.2.6.dist-info/licenses/LICENSE
aditor-0.2.6.dist-info/METADATA
aditor-0.2.6.dist-info/WHEEL
aditor-0.2.6.dist-info/top_level.txt
aditor-0.2.6.dist-info/RECORD
