Metadata-Version: 2.4
Name: aditor
Version: 0.2.6
Summary: 一个示例Python包
Home-page: https://github.com/yourusername/aditor
Author: aditor
Author-email: aditor <your.email@example.com>
Maintainer-email: aditor <your.email@example.com>
License: MIT
Project-URL: Homepage, https://github.com/yourusername/aditor
Project-URL: Repository, https://github.com/yourusername/aditor
Project-URL: Issues, https://github.com/yourusername/aditor/issues
Keywords: python,package,example
Classifier: Development Status :: 3 - Alpha
Classifier: Intended Audience :: Developers
Classifier: License :: OSI Approved :: MIT License
Classifier: Operating System :: OS Independent
Classifier: Programming Language :: Python :: 3
Classifier: Programming Language :: Python :: 3.7
Classifier: Programming Language :: Python :: 3.8
Classifier: Programming Language :: Python :: 3.9
Classifier: Programming Language :: Python :: 3.10
Classifier: Programming Language :: Python :: 3.11
Requires-Python: >=3.7
License-File: LICENSE
Requires-Dist: requests>=2.25.0
Requires-Dist: Pillow>=8.0.0
Provides-Extra: dev
Requires-Dist: pytest>=6.0; extra == "dev"
Requires-Dist: pytest-cov; extra == "dev"
Requires-Dist: black; extra == "dev"
Requires-Dist: flake8; extra == "dev"
Requires-Dist: mypy; extra == "dev"
Dynamic: author
Dynamic: home-page
Dynamic: license-file
Dynamic: requires-python
